Workbook
Name _Regression_Int: 1
Name Area_stampa_MI: #REF!
Name solver_lin: 0
Name solver_num: 0
Name solver_opt: #REF!
Name solver_typ: 1
Name solver_val: 0

Sheet DASHBOARD
A1: APRI 2026 — DASHBOARD ECONOMICO-FINANZIARIA
A2: Modello aggiornato • Revisione finanziaria • Input → Elaborazione → Risultati
A4: INPUT UTENTE | C4: PARAMETRI AGGIORNATI | E4: RISULTATI
A5: Celle gialle | C5: Celle rosse | E5: Celle verdi
A7: SEZIONE | B7: FUNZIONE | C7: COSA DEVI FARE | D7: DOVE LEGGI IL RISULTATO | E7: STATO | F7: NOTE
A8: APRI | B8: Dati e modello principale | C8: Compila solo le celle gialle | D8: Celle verdi / risultati del modello | E8: OPERATIVO | F8: Foglio principale
A9: AGGIORNAMENTO 2026 | B9: Parametri e revisione | C9: Controlla i parametri evidenziati | D9: Confronto originale / aggiornato | E9: VERIFICATO | F9: Fonte e ratio nei commenti
A12: PARAMETRI FINANZIARI 2026
A13: Costo finanziamento benchmark | B13: 0.0434 | C13: Banca d’Italia — nuovi prestiti imprese
A14: Remunerazione liquidità benchmark | B14: 0.0065 | C14: Banca d’Italia — depositi
A15: Inflazione NIC | B15: 0.029 | C15: ISTAT — luglio 2026, dato definitivo
A16: IRES | B16: 0.24 | C16: Aliquota ordinaria di riferimento
A17: IRAP | B17: 0.039 | C17: Aliquota ordinaria di riferimento
A18: IVA ordinaria | B18: 0.22 | C18: Da verificare per categoria merceologica

Sheet AGGIORNAMENTO 2026
A1: AGGIORNAMENTO MODELLO APRI
A2: Data aggiornamento | B2: 13/08/2026
A3: Versione | B3: 2026
A4: Criterio | B4: Sono stati aggiornati i parametri obsoleti; le formule mantengono la logica originaria.
A5: Colore rosso | B5: Valore/formula modificato rispetto all'originale
A7: PARAMETRO | B7: CELLA | C7: ORIGINALE | D7: AGGIORNATO | E7: FONTE/CRITERIO | F7: NOTE
A8: Data elaborazione | B8: APRI!E1 | C8: 14/06/2007 | D8: 13/08/2026 | E8: Data corrente | F8: Aggiornata
A9: Inflazione beni largo consumo (proxy) | B9: APRI!C13 | C9: 2,50% | D9: 2,80% | E9: ISTAT, luglio 2026 | F9: Usata come proxy dell'inflazione corrente; il dato NIC annuo di luglio 2026 è +2,8%.
A10: Incremento costi | B10: APRI!C43 | C10: 2,50% | D10: 2,80% | E10: ISTAT, luglio 2026 | F10: Allineato al dato inflattivo generale; modificabile per scenario.
A11: Tasso passivo c/c | B11: APRI!C49 | C11: 5,00% | D11: 4,34% | E11: Banca d'Italia, maggio 2026 | F11: Proxy prudenziale: tasso nuovi prestiti alle società non finanziarie fino a 1 mln.
A12: Tasso attivo c/c | B12: APRI!C50 | C12: 1,50% | D12: 0,65% | E12: Banca d'Italia, maggio 2026 | F12: Tasso medio passivo sui depositi in essere; usato come proxy del rendimento della liquidità.
A13: IRAP | B13: APRI!C51 | C13: 4,25% | D13: 3,90% | E13: MEF | F13: Aliquota ordinaria nazionale; eventuali maggiorazioni regionali non incluse.
A14: IRES | B14: APRI!C52 | C14: 33,00% | D14: 24,00% | E14: Agenzia Entrate | F14: Aliquota ordinaria IRES vigente.
A15: IVA ordinaria cespiti | B15: APRI!B83 | C15: 20,00% | D15: 22,00% | E15: Normativa IVA italiana | F15: Aliquota ordinaria.
A16: Leasing immobiliare | B16: APRI!D93 | C16: 5,00% | D16: 4,34% | E16: Banca d'Italia, maggio 2026 | F16: Proxy per costo del finanziamento corporate fino a 1 mln.
A17: Leasing mobiliare | B17: APRI!D94 | C17: 5,00% | D17: 4,34% | E17: Banca d'Italia, maggio 2026 | F17: Proxy per costo del finanziamento corporate fino a 1 mln.
A18: Leasing d'azienda | B18: APRI!D95 | C18: 5,00% | D18: 4,34% | E18: Banca d'Italia, maggio 2026 | F18: Proxy per costo del finanziamento corporate fino a 1 mln.
... A20: Mutuo 2 | B20: APRI!D98 | C20: 5,00% | D20: 4,34% | E20: Banca d'Italia, maggio 2026 | F20: Proxy per costo del finanziamento corporate fino a 1 mln.
A23: REVISIONE FINANZIARIA DEL MODELLO
A24: Controllo #VALUE! | B24: Corretto | C24: Le formule dei piani di ammortamento restituivano "" (testo) come saldo residuo; il valore veniva poi moltiplicato per il tasso, generando #VALUE!. I saldi inattivi ora restituiscono 0.
A25: C49 / tasso passivo c/c | B25: 4,34% | C25: Aggiornato al dato maggio 2026 Banca d’Italia per nuovi prestiti alle imprese fino a 1 milione di euro. È un benchmark, non una quotazione bancaria specifica.
A26: C50 / tasso attivo c/c | B26: 0,65% | C26: Aggiornato al dato maggio 2026 Banca d’Italia sui depositi in essere.
A27: C13 / inflazione beni largo consumo | B27: 2,90% | C27: Parametro ricondotto all’inflazione NIC di luglio 2026; il carrello della spesa è però +1,3%, quindi il valore va inteso come ipotesi generale e non come indice specifico retail.
A28: C43 / incremento costi | B28: 2,90% | C28: Allineato al parametro inflattivo generale luglio 2026.
A29: C51 / IRAP | B29: 3,90% | C29: Aliquota ordinaria di riferimento; eventuale maggiorazione/differenziazione regionale non modellata.
A30: C52 / IRES | B30: 24,00% | C30: Aliquota ordinaria IRES aggiornata.
A31: B83 / IVA ordinaria | B31: 22,00% | C31: Aliquota ordinaria IVA vigente; le aliquote specifiche per categorie merceologiche restano da verificare separatamente.
A32: D93:D98 / finanziamenti | B32: 4,34% | C32: Benchmark unico per finanziamenti/leasing nel modello, coerente con il dato Banca d’Italia maggio 2026 per prestiti alle imprese fino a 1 milione. Per un preventivo reale il tasso va sostituito con il TAN/TAEG effettivo.
A33: Formula finanziaria | B33: PMT mantenuta | C33: Le rate restano calcolate con PMT su periodicità trimestrale. È stata corretta la propagazione dei saldi vuoti nei piani di ammortamento senza alterare la logica economica quando il debito è attivo.
A35: Formula audit
A36: Sono state sostituite le restituzioni "" dei saldi residui nei piani di rimborso con 0, evitando errori di tipo e mantenendo invariati i calcoli quando il finanziamento è inattivo.

Sheet APRI
A1: ZONA INPUT DATI: | D1: data elab.: | E1: 2026-08-13 | F1: note: | L1: LEGENDA | M1: ROSSO = parametro aggiornato 2026 | AP1: INPUT UTENTE
A2: INCASSI: | C2: 5800 | D2: incidenza | E2: m.l. | F2: iva | G2: DESCRIZIONE AGGIUNTIVA: | AP2: Celle gialle: inserisci / aggiorna i dati
A3: SALA | C3: =($C$2*D3)*(1-F3) -> 2839.1 | D3: 0.55 | E3: 0.225 | F3: 0.11
A4: S.& L. | C4: =($C$2*D4)*(1-F4) -> 1173.92 | D4: 0.22 | E4: 0.225 | F4: 0.08 | AP4: PARAMETRI 2026
A5: PESCE | C5: =($C$2*D5)*(1-F5) -> 165.3 | D5: 0.03 | E5: 0.225 | F5: 0.05 | AP5: Celle rosse: valori aggiornati
A6: CARNI | C6: =($C$2*D6)*(1-F6) -> 584.64 | D6: 0.12 | E6: 0.225 | F6: 0.16
A7: ORTO | C7: =($C$2*D7)*(1-F7) -> 445.44 | D7: 0.08 | E7: 0.225 | F7: 0.04 | AP7: RISULTATI
A8: TOTALE - vendite: | C8: =SUM(C3:C7) -> 5208.4 | D8: =SUM(D3:D7) -> 1 | E8: =(+C3*E3+C4*E4+C5*E5+C6*E6+C7*E7)/C8 -> 0.225 | F8: =D3*F3+D4*F4+D5*F5+D6*F6+D7*F7 -> 0.102 | AP8: Celle verdi: risultati da leggere
A9: ANNO 1: mesi di vendita | C9: 12 | D9: minor ML nel primo anno
A10: Mesi di preapertura (costi a c\economico) | C10: 0 | E10: 0.03 | F10: =IF(CALCOLI!K48=0,"ERR","") | G10: =IF(F10="ERR","mesi preaperura eccessivi","")
C11: anno 1 | E11: anno 2 | G11: anno 3 | I11: anno 4
A12: ANNI SUCCESSIVI: | C12: input man. | E12: =+C12 -> input man. | G12: =+E12 -> input man. | H12: automatico | I12: =+G12 -> input man. | J12: automatico
A13: INFLAZ BENI LARGO CONSUMO | C13: 0.029 | D13: =IF(C13>0,"","ERR") | E13: =+C13 -> 0.029 | F13: =+C13 -> 0.029 | H13: =$C$13 -> 0.029 | J13: =$C$13 -> 0.029
A14: INCASSI | C14: 4800 | D14: =IF(C14>0,"","ERR") | E14: 5300 | F14: =IF(E14>0,"","ERR") | H14: =+C2 -> 5800 | J14: =IF(I13>0.001,H14*(1+I13),H14*(1+J13)) -> 5968.2
A15: MARGINE LORDO | C15: 0.19 | D15: =IF(C15>0,"","ERR") | E15: 0.205 | F15: =IF(E15>0,"","ERR") | H15: =+E8 -> 0.225 | J15: =$E$8 -> 0.225
A16: =IF(D16="ERR","manca dato inflazione","") | B16: =IF(OR(E16="ERR",G16="ERR",I16="ERR"),"sia % che mln","") | D16: =IF(C13=0,"ERR","") | G16: =IF(AND(G13<>0,G14>0),"ERR","") | I16: =IF(AND(I13<>0,I14>0),"ERR","")
A17: COSTO DEL LAVORO: | C17: obiettivo | D17: calcolato | E17: obiettivo | F17: calcolato | G17: obiettivo | H17: calcolato | I17: obiettivo | J17: calcolato
A18: OBIETT.PRODUTTIVITA' | C18: 238 | D18: =(C124/C9*12)/C25 -> 228.57143 | E18: =C18*(1+E13) -> 244.902 | F18: =E124/E25 -> 244.902 | G18: =E18*(1+H13) -> 252.00416 | H18: =G124/G25 -> 252.00416 | I18: =G18*(1+J13) -> 259.31228 | J18: =I124/I25 -> 259.31228
A19: NR. DIPEND.NECESSARI | C19: =IF(C124>0,C124/C18,"") -> 20.168067 | D19: =(D18-C18)/C18 -> -0.039615846 | E19: =IF(E124>0,E124/E18,"") -> 21.64131 | F19: =(F18-E18)/E18 -> 0 | G19: =IF(G124>0,G124/G18,"") -> 23.015493 | H19: =(H18-G18)/G18 -> 0 | I19: =IF(I124>0,I124/I18,"") -> 23.015493 | J19: =(J18-I18)/I18 -> 0
A20: di cui: | C20: NR.dipendenti | D20: Costo x Unità | E20: NR.dipendenti | F20: Costo x Unità | G20: NR.dipendenti | H20: Costo x Unità | I20: NR.dipendenti | J20: Costo x Unità
A21: CAPO NEGOZIO | C21: 1 | D21: 41.5 | E21: =C21 -> 1 | F21: =D21*(1+$D$43) -> 42.7035 | G21: =+E21 -> 1 | H21: =F21*(1+$E$43) -> 43.941901 | I21: =G21 -> 1 | J21: =H21*(1+$F$43) -> 45.216217
A22: CAPI REPARTO + SOCI | C22: 4 | D22: 31.8 | E22: =C22 -> 4 | F22: =D22*(1+$D$43) -> 32.7222 | G22: =+E22 -> 4 | H22: =F22*(1+$E$43) -> 33.671144 | I22: =G22 -> 4 | J22: =H22*(1+$F$43) -> 34.647607
A23: ADDETTI S/ SGRAVIO | C23: 7 | D23: 25 | E23: =+C23 -> 7 | F23: =D23*(1+$D$43) -> 25.725 | G23: =+E23 -> 7 | H23: =F23*(1+$E$43) -> 26.471025 | I23: =+I124/I18-I21-I22-I24 -> 13.015493 | J23: =H23*(1+$F$43) -> 27.238685
A24: ADDETTI C/ SGRAVIO | C24: 9 | D24: 18.5 | E24: =+E124/E18-E21-E22-E23 -> 9.6413096 | F24: =D24*(1+$D$43) -> 19.0365 | G24: =+G124/G18-G21-G22-G23 -> 11.015493 | H24: =F24*(1+$E$43) -> 19.588558 | I24: 5 | J24: =H24*(1+$F$43) -> 20.156627
A25: TOTALE DIPENDENTI (costo annuo) | C25: =SUM(C21:C24) -> 21 | D25: =C21*D21+C22*D22+C23*D23+C24*D24 -> 510.2 | E25: =SUM(E21:E24) -> 21.64131 | F25: =E21*F21+E22*F22+E23*F23+E24*F24 -> 537.20409 | G25: =SUM(G21:G24) -> 23.015493 | H25: =G21*H21+G22*H22+G23*H23+G24*H24 -> 579.70129 | I25: =SUM(I21:I24) -> 23.015493 | J25: =I21*J21+I22*J22+I23*J23+I24*J24 -> 639.1147
A27: IMMOBILE: | C27: di proprietà | D27: in affitto | E27: riaffittati | F27: Tot.disponib. | G27: anno | H27: affitto | I27: ricavo | J27: totale
A28: MQ. | D28: 1500 | F28: =+C28+D28-E28 -> 1500
A29: di cui: AREA VENDITA | F29: 1000 | G29: 1 | H29: =+D31 -> 92.34 | I29: =+E32 -> 0 | J29: =+H29-I29 -> 92.34
A30: COSTO IMMOBILIARE €/mq | C30: =+C28*B30/1000 -> 0 | G30: 2 | H30: =D31*(1+$D$43) -> 95.01786 | I30: =E32*(1+$D$43) -> 0 | J30: =+H30-I30 -> 95.01786
A31: COSTO DI AFFITTO €/mq mese | B31: 5.13 | D31: =(+D28*B31*12)/1000 -> 92.34 | G31: 3 | H31: =H30*(1+$D$43) -> 97.773378 | I31: =I30*(1+$D$43) -> 0 | J31: =+H31-I31 -> 97.773378
A32: RICAVO RIAFFITTO €/mq mese | E32: =+B32*12*E28/1000 -> 0 | G32: 4 | H32: =H31*(1+$D$43) -> 100.60881 | I32: =I31*(1+$D$43) -> 0 | J32: =+H32-I32 -> 100.60881
A34: AFFITTO AZIENDA | C34: INCASSI | D34: VENDITE | E34: ANNO | F34: TOT.AFFITTO
E35: 1 | F35: =+CALCOLI!K21 -> 0
A36: 1° scaglione | B36: 0 | C36: 0 | D36: 0 | E36: 2 | F36: =+CALCOLI!L21 -> 0 | O36: 0.10786696 | P36: 816553.81
A37: 2° scaglione | B37: su eccedenza 1° scagl. | C37: 0 | D37: 0 | E37: 3 | F37: =+CALCOLI!M21 -> 0
A38: MINIMO GARANTITO (Mln) | B38: 0 | E38: 4 | F38: =+CALCOLI!N21 -> 0
A39: =IF(D39="ERR","controllo % sia su incassi che vendite","") | D39: =IF(AND(C36>0,D36>0),"ERR",IF(AND(C37>0,D37>0),"ERR",IF(AND(C36>0,D37>0),"ERR",IF(AND(D36>0,C37>0),"ERR",""))))
A40: =IF(D40="ERR","controllo % su 2° scaglione e importo 1° scaglione","") | D40: =IF(AND(C37>0,B36=0),"ERR",IF(AND(D37>0,B36=0),"ERR",IF(AND(B36>0,C36>0,C37=0),"ERR",IF(AND(B36>0,D36>0,D37=0),"ERR",""))))
A41: INPUT PARAMETRI VARI | D41: ANNO SUCCESS. SU PRECED. - INC. ANNO
A42: VOCI: | B42: CONTROLLO | C42: ANNO 1 | D42: ANNO 2 | E42: ANNO 3 | F42: 4 ANNO
A43: % INCREM COSTI (Iinflaz Istat)) | B43: =IF(C43>0.0001,"","ERR") | C43: 0.029 | D43: =C43 -> 0.029 | E43: =D43 -> 0.029 | F43: =E43 -> 0.029
A44: % INCREMENTO MANUTENZIONI (su anno 2) | C44: 0.05 | D44: 0.01 | E44: 0.1 | F44: 0.15
A45: % INCIDENZA PUBBLICITA' | B45: =IF(C45>0.0001,"","ERR") | C45: 0.01 | D45: =C45 -> 0.01 | E45: =D45 -> 0.01 | F45: =E45 -> 0.01
A46: % TRASPORTO 0,9% / 1,25%) | B46: =IF(C46>0.0001,"","ERR") | C46: 0.0125 | D46: =C46 -> 0.0125 | E46: =D46 -> 0.0125 | F46: =E46 -> 0.0125
A47: % IMBALLAGGI | B47: =IF(C47>0.0001,"","ERR") | C47: 0.007 | D47: =C47 -> 0.007 | E47: =D47 -> 0.007 | F47: =E47 -> 0.007
A48: % PFA | B48: =IF(C48>0.0001,"","ERR") | C48: 0.013 | D48: =C48 -> 0.013 | E48: =D48 -> 0.013 | F48: =E48 -> 0.013
A49: TASSO PASSIVO C\C | B49: =IF(C49>0.0001,"","ERR") | C49: 0.0434 | D49: =C49 -> 0.0434 | E49: =D49 -> 0.0434 | F49: =E49 -> 0.0434
A50: TASSO ATTIVO C\C | B50: =IF(C50>0.0001,"","ERR") | C50: 0.0065 | D50: =C50 -> 0.0065 | E50: =D50 -> 0.0065 | F50: =E50 -> 0.0065
A51: % IRAP | B51: =IF(C51>0.0001,"","ERR") | C51: 0.039
A52: % IRES | B52: =IF(C52>0.0001,"","ERR") | C52: 0.24
A53: GG.DILAZIONE INCASSI | C53: 2
A54: GG.DILAZIONE FORNITORI | B54: =IF(C54>0.0001,"","ERR") | C54: 35 | D54: =C54 -> 35 | E54: =D54 -> 35 | F54: =E54 -> 35
A55: GG DILAZ.FORNIT.IMPIANTO | B55: =IF(C55>0.0001,"","ERR") | C55: 90
A56: GG. DILAZIONE P.F.A.(rif. 30.6) | B56: =IF(C56>0.0001,"","ERR") | C56: 365 | D56: =+C56 -> 365 | E56: =+D56 -> 365 | F56: =+E56 -> 365
A58: SCORTE | B58: €\mq | C58: TOTALE € | D58: % iva media
A59: valori di input | B59: 0.25 | C59: =B59*$F$29 -> 250 | D59: =CALCOLI!D48 -> 0.102
A61: SPESE GENERALI (base anno) | C61: ANNO 1 | D61: ANNO 2 | E61: ANNO 3 | F61: 4 ANNO
A62: assicurazioni | C62: 5 | D62: =C62*(1+$D$43) -> 5.145 | E62: =D62*(1+$E$43) -> 5.294205 | F62: =E62*(1+$F$43) -> 5.4477369
A63: condominiali | D63: =C63*(1+$D$43) -> 0 | E63: =D63*(1+$E$43) -> 0 | F63: =E63*(1+$F$43) -> 0
A64: imposte varie | C64: 15 | D64: =C64*(1+$D$43) -> 15.435 | E64: =D64*(1+$E$43) -> 15.882615 | F64: =E64*(1+$F$43) -> 16.343211
A65: spese c/c | D65: =C65*(1+$D$43) -> 0 | E65: =D65*(1+$E$43) -> 0 | F65: =E65*(1+$F$43) -> 0
A66: prestazioni di terzi | D66: =C66*(1+$D$43) -> 0 | E66: =D66*(1+$E$43) -> 0 | F66: =E66*(1+$F$43) -> 0
A67: varie\impreviste | C67: 10 | D67: =C67*(1+$D$43) -> 10.29 | E67: =D67*(1+$D$43) -> 10.58841 | F67: =E67*(1+$D$43) -> 10.895474
A68: S\IVA | C68: =SUM(C62:C67) -> 30 | D68: =SUM(D62:D67) -> 30.87 | E68: =SUM(E62:E67) -> 31.76523 | F68: =SUM(F62:F67) -> 32.686422
A69: enel | C69: 60 | D69: =C69*(1+$D$43) -> 61.74 | E69: =D69*(1+$E$43) -> 63.53046 | F69: =E69*(1+$F$43) -> 65.372843
A70: sip | D70: =C70*(1+$D$43) -> 0 | E70: =D70*(1+$E$43) -> 0 | F70: =E70*(1+$F$43) -> 0
A71: utenze | D71: =C71*(1+$D$43) -> 0 | E71: =D71*(1+$E$43) -> 0 | F71: =E71*(1+$F$43) -> 0
A72: pulizia | D72: =C72*(1+$D$43) -> 0 | E72: =D72*(1+$E$43) -> 0 | F72: =E72*(1+$F$43) -> 0
A73: vigilanza | D73: =C73*(1+$D$43) -> 0 | E73: =D73*(1+$E$43) -> 0 | F73: =E73*(1+$F$43) -> 0
A74: manutenzioni | C74: 20 | D74: =C74*(1+D44) -> 20.2 | E74: =D74*(1+E44) -> 22.22 | F74: =E74*(1+F44) -> 25.553
A75: cancelleria/contabilità | D75: =C75*(1+$D$43) -> 0 | E75: =D75*(1+$E$43) -> 0 | F75: =E75*(1+$F$43) -> 0
A76: mat.consumo/varie | C76: 10 | D76: =C76*(1+$D$43) -> 10.29 | E76: =D76*(1+$E$43) -> 10.58841 | F76: =E76*(1+$F$43) -> 10.895474
A77: varie\impreviste | C77: 60 | D77: =C77*(1+$D$43) -> 61.74 | E77: =D77*(1+$E$43) -> 63.53046 | F77: =E77*(1+$F$43) -> 65.372843
A78: C\IVA | C78: =SUM(C69:C77) -> 150 | D78: =SUM(D69:D77) -> 153.97 | E78: =SUM(E69:E77) -> 159.86933 | F78: =SUM(F69:F77) -> 167.19416
A79: TOTALE | C79: =+C78+C68 -> 180 | D79: =+D78+D68 -> 184.84 | E79: =+E78+E68 -> 191.63456 | F79: =+F78+F68 -> 199.88058
A80: INC.% S.G. SU VENDITE | C80: =C79/(C2*(1-F8)) -> 0.034559558 | D80: =+D79/E125 -> 0.038836828 | E80: =+E79/G125 -> 0.036793365 | F80: =+F79/I125 -> 0.037295025
A82: INVESTIMENTI ANNO 1 | B82: iva cespiti | C82: TOTALE | D82: di cui | E82: Investimento | F82: MESI DILAZ.
A83: ALIQUOTA IVA ORDINARIA | B83: 0.22 | D83: LEASING | E83: NETTO | F83: PAGAM.
A84: IMMOBILE | B84: =+B83 -> 0.22 | C84: =+C30 -> 0 | E84: =IF(D84>C84,"ERR",C84-D84) -> 0 | F84: 0 | G84: =IF(E84="ERR","importo leasing maggiore dell'investimento","")
A85: ATTREZZATURE | B85: =+B83 -> 0.22 | C85: 620 | D85: 620 | E85: =IF(D85>C85,"ERR",C85-D85) -> 0 | F85: 0 | G85: =IF(E85="ERR","importo leasing maggiore dell'investimento","")
A86: IMPIANTI (termico / elettrico) | B86: =+B83 -> 0.22 | C86: 230 | E86: =IF(D86>C86,"ERR",C86-D86) -> 230 | F86: 0 | G86: =IF(E86="ERR","importo leasing maggiore dell'investimento","") | H86: OPERE MURARIE
A87: AVVIAMENTO \ AZIENDA | B87: 0 | C87: 0 | D87: 0 | E87: =IF(D87>C87,"ERR",C87-D87) -> 0 | F87: 0 | G87: =IF(E87="ERR","importo leasing maggiore dell'investimento","")
A88: ALTRI IMMOBILIZZI FINANZ. | B88: 0 | C88: 0 | E88: =IF(D88>C88,"ERR",C88-D88) -> 0 | F88: 0
A89: DEPOSITO CAUZIONALE | B89: 0 | C89: 0 | E89: =C89 -> 0 | F89: 0
A90: TOTALE IMMOBILIZZI | C90: =SUM(C84:C89) -> 850 | D90: =SUM(D84:D89) -> 620 | E90: =SUM(E84:E89) -> 230
A92: MUTUI \ LEASING | B92: IMPORTO | C92: ANNI | D92: TASSO | E92: % maxican. | F92: Importo
A93: LEASING IMMOBILIARE | B93: =+D84+D86 -> 0 | C93: 15 | D93: 0.0434 | E93: 0.1 | F93: =+B93*E93 -> 0
A94: LEASING MOBILIARE | B94: =+D85 -> 620 | C94: 7 | D94: 0.0434 | E94: 0.1 | F94: =+B94*E94 -> 62
A95: LEASING D'AZIENDA | B95: =+D87 -> 0 | C95: 5 | D95: 0.0434 | E95: 0.15 | F95: =+B95*E95 -> 0
A96: TOTALE LEASING | B96: =SUM(B93:B95) -> 620 | F96: =SUM(F93:F95) -> 62
A97: MUTUO 1 | C97: 4 | D97: 0.0434
A98: MUTUO 2 | C98: 5 | D98: 0.0434
A100: CAPITALE SOCIALE (20% - 40%) | C100: 250 | D100: =IF(C100<1,"MANCA CAPITALE SOCIALE","")
A101: % COP.PERD: si=% no=0% | C101: 0 | D101: Effettivamente versate
A102: % DIVIDENDO:si=% no=0% | C102: 0 | D102: Prelievi per tasse, personali (oltre la remunerazione a socio, ecc.)
A104: IVA A RIMBORSO | B104: ANNO | C104: 1 | D104: 2 | E104: 3 | F104: 4
A105: SALDO IVA ALLA FINE DELL'ANNO: | C105: =+CALCOLI!D14 -> 101.56586 | D105: =+CALCOLI!E14 -> 36.122479 | E105: =+CALCOLI!F14 -> 5.8211748 | F105: =+CALCOLI!G14 -> -10.953839 | G105: se negativo: iva a debito
A106: di cui: CHIESTA A RIMBORSO | C106: 65 | D106: 14 | E106: 0 | F106: 0 | G106: se il rimborso è maggiore del credito: ERR
B107: NELL'ANNO: | C107: 2 | D107: 3 | E107: 4 | F107: 5
A108: =IF(OR(C108="ERR",D108="ERR",E108="ERR",F108="ERR"),"Importo a rimborso maggiore del credito","") | C108: =IF(C106=0,"",IF(C106>C105,"ERR","")) | D108: =IF(D106=0,"",IF(D106>D105,"ERR","")) | E108: =IF(E106=0,"",IF(E106>E105,"ERR","")) | F108: =IF(F106=0,"",IF(F106>F105,"ERR",""))
...

Sheet CALCOLI
B2: CALCOLO IVA | D2: ANNO 1 | E2: ANNO 2 | F2: ANNO 3 | G2: ANNO 4 | J2: CALCOLO AFFITTO DI AZIENDA
B3: RIPORTO CREDITO | D3: 0 | E3: =IF(D16>0,+D16,0) -> 36.565858 | F3: =IF(E16>0,+E16,0) -> 22.122479 | G3: =IF(F16>0,+F16,0) -> 5.8211748 | K3: 1 | L3: 2 | M3: 3 | N3: 4
B4: CESPITI | D4: =IF(APRI!C119>0,(APRI!C112*APRI!$B$84+APRI!C113*APRI!$B$85+APRI!C114*APRI!$B$86+APRI!C115*APRI!$B$87+APRI!C118*APRI!$B$83),0) -> 64.24 | E4: =IF(APRI!E119>0,(APRI!E112*APRI!$B$84+APRI!E113*APRI!$B$85+APRI!E114*APRI!$B$86+APRI!E115*APRI!$B$87+APRI!E118*APRI!$B$83),0) -> 0 | F4: =IF(APRI!G119>0,(APRI!G112*APRI!$B$84+APRI!G113*APRI!$B$85+APRI!G114*APRI!$B$86+APRI!G115*APRI!$B$87+APRI!G118*APRI!$B$83),0) -> 0 | G4: =IF(APRI!I119>0,(APRI!I112*APRI!$B$84+APRI!I113*APRI!$B$85+APRI!I114*APRI!$B$86+APRI!I115*APRI!$B$87+APRI!I118*APRI!$B$83),0) -> 0 | J4: min.gar. | K4: =+APRI!B38/12*APRI!C9 -> 0 | L4: =+APRI!B38*(1+APRI!F13) -> 0 | M4: =+L4*(1+APRI!H13) -> 0 | N4: =+M4*(1+APRI!J13) -> 0
B5: SU 1^ FORNITURA | D5: =IF(APRI!C59*APRI!D59>1,APRI!C59*APRI!D59,0) -> 25.5 | J5: INCASSI | K5: =IF(APRI!$C$36>APRI!$D$36,APRI!C124,0) -> 0 | L5: =IF(APRI!$C$36>APRI!$D$36,APRI!E124,0) -> 0 | M5: =IF(APRI!$C$36>APRI!$D$36,APRI!G124,0) -> 0 | N5: =IF(APRI!$C$36>APRI!$D$36,APRI!I124,0) -> 0
B6: sdo iniziale | D6: =SUM(D3:D5) -> 89.74 | E6: =SUM(E3:E5) -> 36.565858 | F6: =SUM(F3:F5) -> 22.122479 | G6: =SUM(G3:G5) -> 5.8211748 | J6: 1° SCAGLIONE | K6: =IF(AND(K5>0,APRI!$B$36>0),+APRI!$B$36/12*APRI!C9,IF(AND(K5>0,APRI!$B$36=0),K5,0)) -> 0 | L6: =IF(AND(L5>0,APRI!$B$36>0),+APRI!$B$36*(1+APRI!F13),IF(AND(L5>0,APRI!$B$36=0),L5,0)) -> 0 | M6: =IF(AND(M5>0,APRI!$B$36>0),+L6*(1+APRI!H13),IF(AND(M5>0,APRI!$B$36=0),M5,0)) -> 0 | N6: =IF(AND(N5>0,APRI!$B$36>0),+M6*(1+APRI!J13),IF(AND(N5>0,APRI!$B$36=0),N5,0)) -> 0
B7: SPESE GENERALI | D7: =APRI!C78*APRI!$B$83 -> 33 | E7: =APRI!D78*APRI!$B$83 -> 33.8734 | F7: =APRI!E78*APRI!$B$83 -> 35.171253 | G7: =APRI!F78*APRI!$B$83 -> 36.782715 | J7: % 1° SCAGLIONE | K7: =IF(APRI!C36>APRI!D36,APRI!C36,0) -> 0 | L7: =+K7 -> 0 | M7: =+L7 -> 0 | N7: =+M7 -> 0
B8: TRASPORTI | D8: =-APRI!C127*CALCOLI!$D$48 -> 5.49576 | E8: =-APRI!E127*CALCOLI!$D$48 -> 6.068235 | F8: =-APRI!G127*CALCOLI!$D$48 -> 6.64071 | G8: =-APRI!I127*CALCOLI!$D$48 -> 6.8332906 | J8: tot 1° | K8: =+K6*K7 -> 0 | L8: =+L6*L7 -> 0 | M8: =+M6*M7 -> 0 | N8: =+N6*N7 -> 0
B9: MATERIALE CONSUMO | D9: =-APRI!C128*APRI!$B$83 -> 6.638016 | E9: =-APRI!E128*APRI!$B$83 -> 7.329476 | F9: =-APRI!G128*APRI!$B$83 -> 8.020936 | G9: =-APRI!I128*APRI!$B$83 -> 8.2535431 | J9: 2° SCAGLIONE | K9: =IF(K5>K6,+K5-K6,0) -> 0 | L9: =IF(L5>L6,+L5-L6,0) -> 0 | M9: =IF(M5>M6,+M5-M6,0) -> 0 | N9: =IF(N5>N6,+N5-N6,0) -> 0
B10: LEASING\AFFITTI | D10: =(APRI!C135+APRI!C134)*APRI!$B$83 -> 40.744754 | E10: =(APRI!E135+APRI!E134)*APRI!$B$83 -> 41.333883 | F10: =(+APRI!G134+APRI!G135)*APRI!$B$83 -> 41.940097 | G10: =(APRI!I135+APRI!I134)*APRI!$B$83 -> 42.563892 | J10: %2° SCAGLIONE | K10: =IF(APRI!C37>APRI!D37,APRI!C37,0) -> 0 | L10: =+K10 -> 0 | M10: =+L10 -> 0 | N10: =+M10 -> 0
B11: PUBBLICITA' | D11: =APRI!C136*APRI!$B$83 -> 9.48288 | E11: =APRI!E136*APRI!$B$83 -> 10.47068 | F11: =APRI!G136*APRI!$B$83 -> 11.45848 | G11: =APRI!I136*APRI!$B$83 -> 11.790776 | J11: tot2° | K11: =+K9*K10 -> 0 | L11: =+L9*L10 -> 0 | M11: =+M9*M10 -> 0 | N11: =+N9*N10 -> 0
B12: TOTALE IVA A CREDITO | D12: =SUM(D6:D11) -> 185.10141 | E12: =SUM(E6:E11) -> 135.64153 | F12: =SUM(F6:F11) -> 125.35395 | G12: =SUM(G6:G11) -> 112.04539 | J12: TOTALE | K12: =+K8+K11 -> 0 | L12: =+L8+L11 -> 0 | M12: =+M8+M11 -> 0 | N12: =+N8+N11 -> 0
B13: IVA SU RICAVI | D13: =-APRI!C126*CALCOLI!$D$48 -> -83.535552 | E13: =-APRI!E126*CALCOLI!$D$48 -> -99.519054 | F13: =-APRI!G126*CALCOLI!$D$48 -> -119.53278 | G13: =-APRI!I126*CALCOLI!$D$48 -> -122.99923 | J13: VENDITE | K13: =IF(APRI!$D$36>APRI!$C$36,APRI!C125,0) -> 0 | L13: =IF(APRI!$D$36>APRI!$C$36,APRI!E125,0) -> 0 | M13: =IF(APRI!$D$36>APRI!$C$36,APRI!G125,0) -> 0 | N13: =IF(APRI!$D$36>APRI!$C$36,APRI!I125,0) -> 0
B14: SALDO (+credito \ - debito) | D14: =+D13+D12 -> 101.56586 | E14: =+E13+E12 -> 36.122479 | F14: =+F13+F12 -> 5.8211748 | G14: =+G13+G12 -> -10.953839 | J14: 1° SCAGLIONE | K14: =IF(APRI!$B$36>0,+APRI!$B$36/12*APRI!C9,K13) -> 0 | L14: =IF(APRI!B36>0,+APRI!B36*(1+APRI!F13),L13) -> 0 | M14: =IF(APRI!$B$36>0,+L14*(1+APRI!H13),M13) -> 0 | N14: =IF(APRI!$B$36>0,+M14*(1+APRI!J13),N13) -> 0
B15: IVA A RIMBORSO | D15: =-APRI!C106 -> -65 | E15: =-APRI!D106 -> -14 | F15: =-APRI!E106 -> 0 | G15: =-APRI!F106 -> 0 | J15: % 1° SCAGLIONE | K15: =IF(APRI!D36>APRI!C36,APRI!D36,0) -> 0 | L15: =+K15 -> 0 | M15: =+L15 -> 0 | N15: =+M15 -> 0
B16: RESIDUO | D16: =SUM(D14:D15) -> 36.565858 | E16: =SUM(E14:E15) -> 22.122479 | F16: =SUM(F14:F15) -> 5.8211748 | G16: =SUM(G14:G15) -> -10.953839 | J16: tot 1° | K16: =+K14*K15 -> 0 | L16: =+L14*L15 -> 0 | M16: =+M14*M15 -> 0 | N16: =+N14*N15 -> 0
J17: 2° SCAGLIONE | K17: =IF(K13>K14,+K13-K14,0) -> 0 | L17: =IF(L13>L14,+L13-L14,0) -> 0 | M17: =IF(M13>M14,+M13-M14,0) -> 0 | N17: =IF(N13>N14,+N13-N14,0) -> 0
J18: %2° SCAGLIONE | K18: =IF(APRI!D37>APRI!C37,APRI!D37,0) -> 0 | L18: =+K18 -> 0 | M18: =+L18 -> 0 | N18: =+M18 -> 0
B19: credito iva a rimborso | D19: 1 | E19: 2 | F19: 3 | G19: 4 | H19: 5 | J19: tot 2° | K19: =+K17*K18 -> 0 | L19: =+L17*L18 -> 0 | M19: =+M17*M18 -> 0 | N19: =+N17*N18 -> 0
B20: credito iniziale | D20: 0 | E20: =+D28 -> 65 | F20: =+E28 -> 14 | G20: =+F28 -> 0 | H20: =+G28 -> 0 | J20: TOTALE | K20: =+K16+K19 -> 0 | L20: =+L16+L19 -> 0 | M20: =+M16+M19 -> 0 | N20: =+N16+N19 -> 0
B21: chiesto a rimborso nel'anno | D21: =-D15 -> 65 | E21: =-E15 -> 14 | F21: =-F15 -> 0 | G21: =-G15 -> 0 | J21: AFF.AZ. | K21: =IF(K4>(K12+K20),K4,(K12+K20)) -> 0 | L21: =IF(L4>(L12+L20),L4,(L12+L20)) -> 0 | M21: =IF(M4>(M12+M20),M4,(M12+M20)) -> 0 | N21: =IF(N4>(N12+N20),N4,(N12+N20)) -> 0
B22: rimborso riferito all'anno:
B23: 1 | D23: =IF(APRI!$C$107=1,APRI!$C$106,0) -> 0 | E23: =IF(APRI!$C$107=2,APRI!$C$106,0) -> 65 | F23: =IF(APRI!$C$107=3,APRI!$C$106,0) -> 0 | G23: =IF(APRI!$C$107=4,APRI!$C$106,0) -> 0 | H23: =IF(APRI!$C$107=5,APRI!$C$106,0) -> 0 | J23: affitto di azienda
B24: 2 | D24: =IF(APRI!$D$107=1,APRI!$D$106,0) -> 0 | E24: =IF(APRI!$D$107=2,APRI!$D$106,0) -> 0 | F24: =IF(APRI!$D$107=3,APRI!$D$106,0) -> 14 | G24: =IF(APRI!$D$107=4,APRI!$D$106,0) -> 0 | H24: =IF(APRI!$D$107=5,APRI!$D$106,0) -> 0 | J24: scaglioni | K24: su incasso | L24: su vendite
B25: 3 | D25: =IF(APRI!$E$107=1,APRI!$E$106,0) -> 0 | E25: =IF(APRI!$E$107=2,APRI!$E$106,0) -> 0 | F25: =IF(APRI!$E$107=3,APRI!$E$106,0) -> 0 | G25: =IF(APRI!$E$107=4,APRI!$E$106,0) -> 0 | H25: =IF(APRI!$E$107=5,APRI!$E$106,0) -> 0 | J25: =IF(AND(APRI!B36>0.1,APRI!C2>APRI!B36),APRI!B36,IF(APRI!C2<APRI!B36,APRI!C2,0)) -> 0 | K25: =IF(APRI!C36>APRI!D36,J25*APRI!C36,0) -> 0 | L25: =IF(APRI!D36>APRI!C36,J25*APRI!D36,0) -> 0
B26: 4 | D26: =IF(APRI!$F$107=1,APRI!$F$106,0) -> 0 | E26: =IF(APRI!$F$107=2,APRI!$F$106,0) -> 0 | F26: =IF(APRI!$F$107=3,APRI!$F$106,0) -> 0 | G26: =IF(APRI!$F$107=4,APRI!$F$106,0) -> 0 | H26: =IF(APRI!$F$107=5,APRI!$F$106,0) -> 0 | J26: =IF((+APRI!C2-APRI!B36)>0.1,APRI!C2-APRI!B36,0) -> 5800 | K26: =IF(APRI!C37>APRI!D37,J26*APRI!C37,0) -> 0 | L26: =IF(APRI!D37>APRI!C37,J26*APRI!D37,0) -> 0
B27: 5 | J27: =SUM(J25:J26) -> 5800 | K27: =SUM(K25:K26) -> 0 | L27: =SUM(L25:L26) -> 0
B28: credito finale | D28: =+D20+D21-D23-D24-D25-D26-D27 -> 65 | E28: =+E20+E21-E23-E24-E25-E26-E27 -> 14 | F28: =+F20+F21-F23-F24-F25-F26-F27 -> 0 | G28: =+G20+G21-G23-G24-G25-G26-G27 -> 0 | H28: =+H20+H21-H23-H24-H25-H26-H27 -> 0 | J28: TOTALE | K28: =IF(AND(K27>0,K27>APRI!$B$38),K27,IF(AND(K27>0,K27<APRI!$B$38),APRI!$B$38,0)) -> 0 | L28: =IF(AND(L27>0,L27>APRI!$B$38),L27,IF(AND(L27>0,L27<APRI!$B$38),APRI!$B$38,0)) -> 0
B30: CASH FLOW: anno | D30: 1 | E30: 2 | F30: 3 | G30: 4 | I30: TASSE | L30: =+APRI!C51 -> 0.039 | M30: =+APRI!C52 -> 0.24 | N30: TOTALE
B31: RIMBORSO MUTUO | D31: =-E142 -> 0 | E31: =-E147 -> 0 | F31: =-E152 -> 0 | G31: =-K142 -> 0 | I31: ANNO | J31: UTILE-+of | K31: LAVORO | L31: IRAP | M31: IRPEG
B32: INCREMENTO CESPITI | E32: =-APRI!E119 -> 0 | F32: =-APRI!G119 -> 0 | G32: =-APRI!I119 -> 0 | I32: 1 | J32: =+APRI!C138+APRI!C139 -> -155.15583 | K32: =+APRI!C131 -> 510.2 | L32: =IF((+J32+K32)>0,(J32+K32)*$L$30,0) -> 13.846723 | M32: =IF(J32>0,+J32*$M$30,0) -> 0 | N32: =+L32+M32 -> 13.846723
B33: INCASSO P.F.A. anno preced. | E33: =-D34 -> 56.0352 | F33: =-E34 -> 61.8722 | G33: =-F34 -> 67.7092 | I33: 2 | J33: =+APRI!E138+APRI!E139 -> -45.161596 | K33: =+APRI!E131 -> 537.20409 | L33: =IF((+J33+K33)>0,(J33+K33)*$L$30,0) -> 19.189657 | M33: =IF(J33>0,+J33*$M$30,0) -> 0 | N33: =+L33+M33 -> 19.189657
B34: P.F.A. anno corrente | D34: =-F55 -> -56.0352 | E34: =-H55 -> -61.8722 | F34: =-J55 -> -67.7092 | G34: =-L55 -> -69.672767 | I34: 3 | J34: =+APRI!G138+APRI!G139 -> 97.289611 | K34: =+APRI!G131 -> 579.70129 | L34: =IF((+J34+K34)>0,(J34+K34)*$L$30,0) -> 26.402645 | M34: =IF(J34>0,+J34*$M$30,0) -> 23.349507 | N34: =+L34+M34 -> 49.752152
B35: AMMORTAMENTI | D35: =+APRI!C133 -> 27.947143 | E35: =+APRI!E133 -> 27.947143 | F35: =+APRI!G133 -> 27.947143 | G35: =+APRI!I133 -> 27.947143 | I35: 4 | J35: =+APRI!I138+APRI!I139 -> 59.911461 | K35: =+APRI!I131 -> 639.1147 | L35: =IF((+J35+K35)>0,(J35+K35)*$L$30,0) -> 27.26202 | M35: =IF(J35>0,+J35*$M$30,0) -> 14.378751 | N35: =+L35+M35 -> 41.640771
B36: MARGINE OPERATIVO | D36: =APRI!C138 -> -155.49617 | E36: =APRI!E138 -> -40.725621 | F36: =APRI!G138 -> 96.031605 | G36: =APRI!I138 -> 57.029336
B37: ALTRI FONDI (TFR) | D37: =(APRI!C22*APRI!D22+APRI!C23*APRI!D23)*5%+(APRI!C24*APRI!D24)/15 -> 26.21 | E37: =(APRI!E22*APRI!F22+APRI!E23*APRI!F23)*5%+(APRI!E24*APRI!F24)/15 -> 27.783976 | F37: =(APRI!G22*APRI!H22+APRI!G23*APRI!H23)*5%+(APRI!G24*APRI!H24)/15 -> 30.384263 | G37: =(APRI!I22*APRI!J22+APRI!I23*APRI!J23)*5%+(APRI!I24*APRI!J24)/15 -> 31.374643
B38: CREDITO IVA dell'anno | D38: =IF(D14>0,-D14,0) -> -101.56586 | E38: =IF(E14>0,-E14,0) -> -36.122479 | F38: =IF(F14>0,-F14,0) -> -5.8211748 | G38: =IF(G14>0,-G14,0) -> 0 | I38: riporto a nuovo del risultato:
B39: SALDO MOV.FINANZ. | D39: =SUM(D31:D38) -> -258.94009 | E39: =SUM(E31:E38) -> -26.953981 | F39: =SUM(F31:F38) -> 142.70484 | G39: =SUM(G31:G38) -> 114.38755 | I39: anno | J39: risultato
B40: VALORE MEDIO | D40: =D39/2 -> -129.47004 | E40: =E39/2 -> -13.476991 | F40: =F39/2 -> 71.352418 | G40: =G39/2 -> 57.193777 | I40: 1 | J40: =IF(APRI!C141>0,APRI!C141-(APRI!C141*APRI!$C$102),APRI!C141-(APRI!C141*APRI!$C$101)) -> -169.00255
B41: RATEO COSTI (ESPOSIZ.VS.FORN.) | D41: =((-APRI!C128+APRI!C131+APRI!C132+APRI!C136)/12)/(APRI!C9+APRI!C10)*12 -> 63.623067 | E41: =(-APRI!E128+APRI!E131+APRI!E132+APRI!E136)/12 -> 66.912824 | F41: =(-APRI!G128+APRI!G131+APRI!G132+APRI!G136)/12 -> 71.656554 | G41: =(-APRI!I128+APRI!I131+APRI!I132+APRI!I136)/12 -> 77.508818 | I41: 2 | J41: =IF(APRI!E141>0,APRI!E141-(APRI!E141*APRI!$C$102),APRI!E141-(APRI!E141*APRI!$C$101)) -> -64.351253
B42: IVA A DEBITOval.medio | D42: =IF(D14<0,D14/APRI!C9,0) -> 0 | E42: =IF(E14<0,E14/12,0) -> 0 | F42: =IF(F14<0,F14/12,0) -> 0 | G42: =IF(G14<0,G14/12,0) -> -0.91281994 | I42: 3 | J42: =IF(APRI!G141>0,APRI!G141-(APRI!G141*APRI!$C$102),APRI!G141-(APRI!G141*APRI!$C$101)) -> 47.537459
B43: TOTALE CASH FLOW | D43: =SUM(D40:D42) -> -65.846977 | E43: =SUM(E40:E42) -> 53.435834 | F43: =SUM(F40:F42) -> 143.00897 | G43: =SUM(G40:G42) -> 133.78978 | I43: 4 | J43: =IF(APRI!I141>0,APRI!I141-(APRI!J141*APRI!$C$102),APRI!I141-(APRI!I141*APRI!$C$101)) -> 18.27069
B45: valore scorte | D45: anno 1 | E45: anno 2 | F45: anno 3 | G45: anno 4
B46: mln\mq | D46: =+APRI!B59 -> 0.25 | E46: =APRI!B59*(1+APRI!F13) -> 0.25725 | F46: =E46*(1+APRI!H13) -> 0.26471025 | G46: =F46*(1+APRI!J13) -> 0.27238685 | I46: APERTURA | K46: =+APRI!C9 -> 12
B47: totale valore | D47: =D46*APRI!$F$29 -> 250 | E47: =E46*APRI!$F$29 -> 257.25 | F47: =F46*APRI!$F$29 -> 264.71025 | G47: =G46*APRI!$F$29 -> 272.38685 | I47: PREAPERTURA | K47: =+APRI!C10 -> 0
B48: % INC.IVA SU INCASSI | D48: =APRI!F8 -> 0.102 | E48: =D48 -> 0.102 | F48: =E48 -> 0.102 | G48: =F48 -> 0.102 | I48: controllo totale mesi anno | K48: =IF((APRI!C9+APRI!C10)>12,0,+APRI!C9+APRI!C10) -> 12
C50: SALDO DELLA GESTIONE FINANZIARIA
E51: sdo iniziale | F51: sdo finale | G51: sdo medio | H51: sdo finale | I51: sdo medio | J51: sdo finale | K51: sdo medio | L51: sdo finale | M51: sdo medio
C52: =+APRI!A144 -> CASSA | E52: =+F52 -> 26.666667 | F52: =+APRI!C144 -> 26.666667 | G52: =(E52+F52)/2 -> 26.666667 | H52: =+APRI!E144 -> 29.041096 | I52: =(+F52+H52)/2 -> 27.853881 | J52: =+APRI!G144 -> 31.780822 | K52: =(+H52+J52)/2 -> 30.410959 | L52: =+APRI!I144 -> 32.702466 | M52: =(+J52+L52)/2 -> 32.241644
C53: =+APRI!A145 -> CESPITI \ IMMOB.FINANZIARI | E53: =+F53 -> 292 | F53: =+APRI!C145 -> 292 | G53: =(E53+F53)/2 -> 292 | H53: =+APRI!E145 -> 292 | I53: =(+F53+H53)/2 -> 292 | J53: =+APRI!G145 -> 292 | K53: =(+H53+J53)/2 -> 292 | L53: =+APRI!I145 -> 292 | M53: =(+J53+L53)/2 -> 292
C54: =+APRI!A146 -> SCORTE | E54: =+F54 -> 250 | F54: =+APRI!C146 -> 250 | G54: =(E54+F54)/2 -> 250 | H54: =+APRI!E146 -> 257.25 | I54: =(+F54+H54)/2 -> 253.625 | J54: =+APRI!G146 -> 264.71025 | K54: =(+H54+J54)/2 -> 260.98012 | L54: =+APRI!I146 -> 272.38685 | M54: =(+J54+L54)/2 -> 268.54855
C55: =+APRI!A147 -> CREDITO P.F.A. | E55: 0 | F55: =IF(APRI!$C$56+180>365,APRI!C129,APRI!C129/365*APRI!$C$56) -> 56.0352 | G55: =(E55+F55)/2 -> 28.0176 | H55: =IF(APRI!$C$56+180>365,APRI!E129,APRI!E129/365*APRI!$C$56) -> 61.8722 | I55: =(+F55+H55)/2 -> 58.9537 | J55: =IF(APRI!$C$56+180>365,APRI!G129,APRI!G129/365*APRI!$C$56) -> 67.7092 | K55: =(+H55+J55)/2 -> 64.7907 | L55: =IF(APRI!$C$56+180>365,APRI!I129,APRI!I129/365*APRI!$C$56) -> 69.672767 | M55: =(+J55+L55)/2 -> 68.690983
C56: =+APRI!A148 -> CREDITO IVA A RIMBORSO | E56: 0 | F56: =+APRI!C148 -> 65 | G56: =(E56+F56)/2 -> 32.5 | H56: =+APRI!E148 -> 14 | I56: =(+F56+H56)/2 -> 39.5 | J56: =+APRI!G148 -> 0 | K56: =(+H56+J56)/2 -> 7 | L56: =+APRI!I148 -> 0 | M56: =(+J56+L56)/2 -> 0
C57: =+APRI!A149 -> CREDITO IVA (a breve) | E57: 0 | F57: =+APRI!C149 -> 36.565858 | G57: =(E57+F57)/2 -> 18.282929 | H57: =+APRI!E149 -> 22.122479 | I57: =(+F57+H57)/2 -> 29.344169 | J57: =+APRI!G149 -> 5.8211748 | K57: =(+H57+J57)/2 -> 13.971827 | L57: =+APRI!I149 -> 0 | M57: =(+J57+L57)/2 -> 2.9105874
C58: =+APRI!A150 -> TOTALE IMMOBILIZZI | E58: =SUM(E52:E57) -> 568.66667 | F58: =SUM(F52:F57) -> 726.26772 | G58: =SUM(G52:G57) -> 647.4672 | H58: =SUM(H52:H57) -> 676.28577 | I58: =SUM(I52:I57) -> 701.27675 | J58: =SUM(J52:J57) -> 662.02145 | K58: =SUM(K52:K57) -> 669.15361 | L58: =SUM(L52:L57) -> 666.76208 | M58: =SUM(M52:M57) -> 664.39176
C59: =+APRI!A151 -> FORNITORI MERCE | E59: =+F59 -> 368.94308 | F59: =+APRI!C151 -> 368.94308 | G59: =(E59+F59)/2 -> 368.94308 | H59: =+APRI!E151 -> 399.83067 | I59: =(+F59+H59)/2 -> 384.38688 | J59: =+APRI!G151 -> 426.54299 | K59: =(+H59+J59)/2 -> 413.18683 | L59: =+APRI!I151 -> 438.91273 | M59: =(+J59+L59)/2 -> 432.72786
C60: FORNITURA DI IMPIANTO | G60: =((+D47*(1+D48))/365*APRI!C55)/12*K46 -> 67.931507
C61: =+APRI!A152 -> FORNITORI SERVIZI E DEBITI DIVERSI | E61: =+F61 -> 63.623067 | F61: =+APRI!C152 -> 63.623067 | G61: =(E61+F61)/2 -> 63.623067 | H61: =+APRI!E152 -> 66.912824 | I61: =(+F61+H61)/2 -> 65.267945 | J61: =+APRI!G152 -> 71.656554 | K61: =(+H61+J61)/2 -> 69.284689 | L61: =+APRI!I152 -> 76.595998 | M61: =(+J61+L61)/2 -> 74.126276
C62: FORNITORI ATTREZZATURE | G62: =((APRI!E84/365*APRI!F84*30+APRI!E85/365*APRI!F85*30+APRI!E86/365*APRI!F86*30+APRI!E87/365*APRI!F87*30+APRI!E88/365*APRI!F88*30+APRI!E89/365*APRI!F89*30))/12*K46 -> 0
C63: =+APRI!A153 -> MUTUI E FINANZIAMENTI | E63: =+D138 -> 0 | F63: =+APRI!C153 -> 0 | G63: =(E63+F63)/2 -> 0 | H63: =+APRI!E153 -> 0 | I63: =(+F63+H63)/2 -> 0 | J63: =+APRI!G153 -> 0 | K63: =(+H63+J63)/2 -> 0 | L63: =+APRI!I153 -> 0 | M63: =(+J63+L63)/2 -> 0
C64: =+APRI!A154 -> FDO AMMORTAMENTO | E64: 0 | F64: =+APRI!C154 -> 27.947143 | G64: =(E64+F64)/2 -> 13.973571 | H64: =+APRI!E154 -> 55.894286 | I64: =(+F64+H64)/2 -> 41.920714 | J64: =+APRI!G154 -> 83.841429 | K64: =(+H64+J64)/2 -> 69.867857 | L64: =+APRI!I154 -> 111.78857 | M64: =(+J64+L64)/2 -> 97.815
C65: =+APRI!A155 -> ALTRI FONDI (TFR) | E65: 0 | F65: =+APRI!C155 -> 26.21 | G65: =(E65+F65)/2 -> 13.105 | H65: =+APRI!E155 -> 53.993976 | I65: =(+F65+H65)/2 -> 40.101988 | J65: =+APRI!G155 -> 84.378239 | K65: =(+H65+J65)/2 -> 69.186108 | L65: =+APRI!I155 -> 115.75288 | M65: =(+J65+L65)/2 -> 100.06556
C66: =+APRI!A156 -> CAPITALE NETTO | E66: =+F66 -> 250 | F66: =+APRI!C156 -> 250 | G66: =(E66+F66)/2 -> 250 | H66: =+APRI!E156 -> 250 | I66: =(+F66+H66)/2 -> 250 | J66: =+APRI!G156 -> 250 | K66: =(+H66+J66)/2 -> 250 | L66: =+APRI!I156 -> 250 | M66: =(+J66+L66)/2 -> 250
C67: MARGINE OPERATIVO | E67: 0 | F67: =+APRI!C138 -> -155.49617 | G67: =(E67+F67)/2 -> -77.748086 | H67: =+APRI!E138 -> -40.725621 | I67: =(+F67+H67)/2 -> -98.110896 | J67: =+APRI!G138 -> 96.031605 | K67: =(+H67+J67)/2 -> 27.652992 | L67: =+APRI!I138 -> 57.029336 | M67: =(+J67+L67)/2 -> 76.53047
C68: =+APRI!A158 -> +UTILI \ -PERDITE RIPORTATE A NUOVO | F68: =+APRI!C158 -> 0 | G68: =(E68+F68)/2 -> 0 | H68: =+APRI!E158 -> -169.00255 | I68: =(+F68+H68)/2 -> -84.501274 | J68: =+APRI!G138 -> 96.031605 | K68: =(+H68+J68)/2 -> -36.485472 | L68: =+APRI!I138 -> 57.029336 | M68: =(+J68+L68)/2 -> 76.53047
C69: =+APRI!A159 -> TOTALE FONTI | E69: =SUM(E59:E68) -> 682.56615 | F69: =SUM(F59:F68) -> 581.22712 | G69: =SUM(G59:G68) -> 699.82814 | H69: =SUM(H59:H68) -> 616.90359 | I69: =SUM(I59:I68) -> 599.06535 | J69: =SUM(J59:J68) -> 1108.4824 | K69: =SUM(K59:K68) -> 862.693 | L69: =SUM(L59:L68) -> 1107.1089 | M69: =SUM(M59:M68) -> 1107.7956
C70: =+APRI!A160 -> SALDO BANCA (+ATTIVO \ - PASSIVO) | E70: =+E69-E58 -> 113.89948 | F70: =+F69-F58 -> -145.04061 | G70: =+G69-G58 -> 52.360942 | H70: =+H69-H58 -> -59.382184 | I70: =+I69-I58 -> -102.2114 | J70: =+J69-J58 -> 446.46097 | K70: =+K69-K58 -> 193.53939 | L70: =+L69-L58 -> 440.34678 | M70: =+M69-M58 -> 443.40388
C72: INTERESSI ATTIVI | G72: =IF(G70>0,(G70*APRI!C50)/12*CALCOLI!K46,0) -> 0.34034612 | I72: =IF(I70>0,(I70*APRI!D50),0) -> 0 | K72: =IF(K70>0,(K70*APRI!E50),0) -> 1.2580061 | M72: =IF(M70>0,(M70*APRI!F50),0) -> 2.8821252
C73: INTERESSI PASSIVI | G73: =IF(G70<0,(G70*APRI!C49)/12*CALCOLI!K46,0) -> 0 | I73: =IF(I70<0,(I70*APRI!D49)) -> -4.4359746 | K73: =IF(K70<0,(K70*APRI!E49)) -> FALSE | M73: =IF(M70<0,(M70*APRI!F49)) -> FALSE
C74: INTERESSI SU MUTUI | G74: =-F142 -> 0 | I74: =-F147 -> 0 | K74: =-F152 -> 0 | M74: =-L142 -> 0
C75: TOTALE INTERESSI | G75: =SUM(G72:G74) -> 0.34034612 | I75: =SUM(I72:I74) -> -4.4359746 | K75: =SUM(K72:K74) -> 1.2580061 | M75: =SUM(M72:M74) -> 2.8821252
E77: ANNO 1 | G77: ANNO 2 | I77: ANNO 3 | K77: ANNO 4
E78: AMM.TO | F78: FDO AM.TO | G78: AMM.TO | H78: FDO AM.TO | I78: AMM.TO | J78: FDO AM.TO | K78: AMM.TO | L78: FDO AM.TO
C79: =+APRI!A112 -> IMMOBILE | E79: =IF(APRI!$C$9<12,(APRI!C112*APRI!D112)/2,APRI!C112*APRI!D112) -> 0 | F79: =E79 -> 0 | G79: =IF(APRI!$C$112*APRI!$D$112+F79>APRI!$C$112,APRI!$C$112-F79,APRI!$C$112*APRI!$D$112) -> 0 | H79: =G79+F79 -> 0 | I79: =IF(APRI!$C$112*APRI!$D$112+H79>APRI!$C$112,APRI!$C$112-H79,APRI!$C$112*APRI!$D$112) -> 0 | J79: =I79+H79 -> 0 | K79: =IF(APRI!$C$112*APRI!$D$112+J79>APRI!$C$112,APRI!$C$112-J79,APRI!$C$112*APRI!$D$112) -> 0 | L79: =K79+J79 -> 0
C80: =+APRI!A113 -> ATTREZZATURE | E80: =IF(APRI!$C$9<12,(APRI!C113*APRI!D113)/2,APRI!C113*APRI!D113) -> 0 | F80: =E80 -> 0 | G80: =IF(APRI!$C$113*APRI!$D$113+F80>APRI!$C$113,APRI!$C$113-F80,APRI!$C$113*APRI!$D$113) -> 0 | H80: =G80+F80 -> 0 | I80: =IF(APRI!$C$113*APRI!$D$113+H80>APRI!$C$113,APRI!$C$113-H80,APRI!$C$113*APRI!$D$113) -> 0 | J80: =I80+H80 -> 0 | K80: =IF(APRI!$C$113*APRI!$D$113+J80>APRI!$C$113,APRI!$C$113-J80,APRI!$C$113*APRI!$D$113) -> 0 | L80: =K80+J80 -> 0
C81: =+APRI!A114 -> IMPIANTI (termico / elettrico) | E81: =IF(APRI!$C$9<12,(APRI!C114*APRI!D114)/2,APRI!C114*APRI!D114) -> 19.09 | F81: =E81 -> 19.09 | G81: =IF(APRI!$C$114*APRI!$D$114+F81>APRI!$C$114,APRI!$C$114-F81,APRI!$C$114*APRI!$D$114) -> 19.09 | H81: =G81+F81 -> 38.18 | I81: =IF(APRI!$C$114*APRI!$D$114+H81>APRI!$C$114,APRI!$C$114-H81,APRI!$C$114*APRI!$D$114) -> 19.09 | J81: =I81+H81 -> 57.27 | K81: =IF(APRI!$C$114*APRI!$D$114+J81>APRI!$C$114,APRI!$C$114-J81,APRI!$C$114*APRI!$D$114) -> 19.09 | L81: =K81+J81 -> 76.36
C82: =+APRI!A115 -> AVVIAMENTO \ AZIENDA | E82: =IF(APRI!$C$9<12,(APRI!C115*APRI!D115)/2,APRI!C115*APRI!D115) -> 0 | F82: =E82 -> 0 | G82: =IF(APRI!$C$115*APRI!$D$115+F82>APRI!$C$115,APRI!$C$115-F82,APRI!$C$115*APRI!$D$115) -> 0 | H82: =G82+F82 -> 0 | I82: =IF(APRI!$C$115*APRI!$D$115+H82>APRI!$C$115,APRI!$C$115-H82,APRI!$C$115*APRI!$D$115) -> 0 | J82: =I82+H82 -> 0 | K82: =IF(APRI!$C$115*APRI!$D$115+J82>APRI!$C$115,APRI!$C$115-J82,APRI!$C$115*APRI!$D$115) -> 0 | L82: =K82+J82 -> 0
C83: MAXICANONE IMMOBILIARE | E83: =(APRI!F93/APRI!C93)/12*APRI!$C$9 -> 0 | F83: =+E83 -> 0 | G83: =+APRI!$F$93/APRI!$C$93 -> 0 | H83: =+F83+G83 -> 0 | I83: =+APRI!$F$93/APRI!$C$93 -> 0 | J83: =+H83+I83 -> 0 | K83: =+APRI!$F$93/APRI!$C$93 -> 0 | L83: =+J83+K83 -> 0
C84: MAXICANONE MOBILIARE | E84: =(APRI!F94/APRI!C94)/12*APRI!$C$9 -> 8.8571429 | F84: =+E84 -> 8.8571429 | G84: =+APRI!$F$94/APRI!$C$94 -> 8.8571429 | H84: =+F84+G84 -> 17.714286 | I84: =+APRI!$F$94/APRI!$C$94 -> 8.8571429 | J84: =+H84+I84 -> 26.571429 | K84: =+APRI!$F$94/APRI!$C$94 -> 8.8571429 | L84: =+J84+K84 -> 35.428571
C85: MAXICANONE DI AZIENDA | E85: =(APRI!F95/APRI!C95)/12*APRI!$C$9 -> 0 | F85: =+E85 -> 0 | G85: =+APRI!$F$95/APRI!$C$95 -> 0 | H85: =+F85+G85 -> 0 | I85: =+APRI!$F$95/APRI!$C$95 -> 0 | J85: =+H85+I85 -> 0 | K85: =+APRI!$F$95/APRI!$C$95 -> 0 | L85: =+J85+K85 -> 0
E86: =SUM(E79:E85) -> 27.947143 | F86: =SUM(F79:F85) -> 27.947143 | G86: =SUM(G79:G85) -> 27.947143 | H86: =SUM(H79:H85) -> 55.894286 | I86: =SUM(I79:I85) -> 27.947143 | J86: =SUM(J79:J85) -> 83.841429 | K86: =SUM(K79:K85) -> 27.947143 | L86: =SUM(L79:L85) -> 111.78857
C88: mutuo 1 | I88: mutuo 2
C89: CAPITALE | E89: =APRI!B97 -> 0 | F89: TOTALE ESBORSO | I89: CAPITALE | K89: =APRI!B98 -> 0 | L89: TOTALE ESBORSO
C90: NR. ANNI | E90: =APRI!C97 -> 4 | F90: ANNUO | G90: =+G92*(12/E91) -> 0 | I90: NR. ANNI | K90: =APRI!C98 -> 5 | L90: ANNUO | M90: =+M92*(12/K91) -> 0
C91: MESI NELLA RATA | E91: 3 | F91: TOTALE NR. RATE | G91: =+E90*(12/E91) -> 16 | I91: MESI NELLA RATA | K91: 3 | L91: TOTALE NR. RATE | M91: =+K90*(12/K91) -> 20
C92: TASSO | E92: =APRI!D97 -> 0.0434 | F92: IMPORTO RATA | G92: =IF(E89>0,PMT(E92/(12/E91),G91,-E89),0) -> 0 | I92: TASSO | K92: =APRI!D98 -> 0.0434 | L92: IMPORTO RATA | M92: =IF(K89>0,PMT(K92/(12/K91),M91,-K89),0) -> 0
C93: NR. | D93: CAPITALE | E93: QUOTA | G93: CAPITALE | I93: NR. | J93: CAPITALE | K93: QUOTA | M93: CAPITALE
C94: RATA | D94: INIZIALE | E94: CAPITALE | F94: INTERESSI | G94: RESIDUO | I94: RATA | J94: INIZIALE | K94: CAPITALE | L94: INTERESSI | M94: RESIDUO
B95: =IF(APRI!$C$9=12,1,0) -> 1 | C95: 1 | D95: =+E89 -> 0 | E95: =IF(B95=0,0,+$G$92-F95) -> 0 | F95: =IF(B95=0,0,+D95*$E$92/12*$E$91) -> 0 | G95: =IF(D95>1,D95-E95,0) -> 0 | H95: =IF(APRI!$C$9=12,1,0) -> 1 | I95: 1 | J95: =+K89 -> 0 | K95: =IF(H95=0,0,+$M$92-L95) -> 0 | L95: =IF(H95=0,0,+J95*$K$92/12*$K$91) -> 0 | M95: =IF(J95>1,J95-K95,0) -> 0
B96: =IF(APRI!$C$9>=9,1,0) -> 1 | C96: =+C95+1 -> 2 | D96: =+G95 -> 0 | E96: =IF(B96=0,0,+$G$92-F96) -> 0 | F96: =IF(B96=0,0,+D96*$E$92/12*$E$91) -> 0 | G96: =IF(D96>1,D96-E96,0) -> 0 | H96: =IF(APRI!$C$9>=9,1,0) -> 1 | I96: =+I95+1 -> 2 | J96: =+M95 -> 0 | K96: =IF(H96=0,0,+$M$92-L96) -> 0 | L96: =IF(H96=0,0,+J96*$K$92/12*$K$91) -> 0 | M96: =IF(J96>1,J96-K96,0) -> 0
B97: =IF(APRI!$C$9>=6,1,0) -> 1 | C97: =+C96+1 -> 3 | D97: =+G96 -> 0 | E97: =IF(B97=0,0,+$G$92-F97) -> 0 | F97: =+D97*$E$92/12*$E$91 -> 0 | G97: =IF(D97>1,D97-E97,0) -> 0 | H97: =IF(APRI!$C$9>=6,1,0) -> 1 | I97: =+I96+1 -> 3 | J97: =+M96 -> 0 | K97: =IF(H97=0,0,+$M$92-L97) -> 0 | L97: =IF(H97=0,0,+J97*$K$92/12*$K$91) -> 0 | M97: =IF(J97>1,J97-K97,0) -> 0
B98: =IF(APRI!$C$9>=3,1,0) -> 1 | C98: =+C97+1 -> 4 | D98: =+G97 -> 0 | E98: =+$G$92-F98 -> 0 | F98: =+D98*$E$92/12*$E$91 -> 0 | G98: =IF(D98>1,D98-E98,0) -> 0 | H98: =IF(APRI!$C$9>=3,1,0) -> 1 | I98: =+I97+1 -> 4 | J98: =+M97 -> 0 | K98: =IF(H98=0,0,+$M$92-L98) -> 0 | L98: =IF(H98=0,0,+J98*$K$92/12*$K$91) -> 0 | M98: =IF(J98>1,J98-K98,0) -> 0
C99: TOTALE ANNO | D99: 1 | E99: =SUM(E95:E98) -> 0 | F99: =SUM(F95:F98) -> 0 | G99: =+G98 -> 0 | I99: TOTALE ANNO | J99: 1 | K99: =SUM(K95:K98) -> 0 | L99: =SUM(L95:L98) -> 0 | M99: =+M98 -> 0
C100: =+C98+1 -> 5 | D100: =+G98 -> 0 | E100: =IF(D100>0,+$G$92-F100,0) -> 0 | F100: =+D100*$E$92/12*$E$91 -> 0 | G100: =IF(D100>1,D100-E100,0) -> 0 | I100: =+I98+1 -> 5 | J100: =+M98 -> 0 | K100: =IF(J100>0,+$M$92-L100,0) -> 0 | L100: =+J100*$K$92/12*$K$91 -> 0 | M100: =IF(J100>1,J100-K100,0) -> 0
C101: =+C100+1 -> 6 | D101: =+G100 -> 0 | E101: =IF(D101>0,+$G$92-F101,0) -> 0 | F101: =+D101*$E$92/12*$E$91 -> 0 | G101: =IF(D101>1,D101-E101,0) -> 0 | I101: =+I100+1 -> 6 | J101: =+M100 -> 0 | K101: =IF(J101>0,+$M$92-L101,0) -> 0 | L101: =+J101*$K$92/12*$K$91 -> 0 | M101: =IF(J101>1,J101-K101,0) -> 0
C102: 7 | D102: =+G101 -> 0 | E102: =IF(D102>0,+$G$92-F102,0) -> 0 | F102: =+D102*$E$92/12*$E$91 -> 0 | G102: =IF(D102>1,D102-E102,0) -> 0 | I102: 7 | J102: =+M101 -> 0 | K102: =IF(J102>0,+$M$92-L102,0) -> 0 | L102: =+J102*$K$92/12*$K$91 -> 0 | M102: =IF(J102>1,J102-K102,0) -> 0
C103: 8 | D103: =+G102 -> 0 | E103: =IF(D103>0,+$G$92-F103,0) -> 0 | F103: =+D103*$E$92/12*$E$91 -> 0 | G103: =IF(D103>1,D103-E103,0) -> 0 | I103: 8 | J103: =+M102 -> 0 | K103: =IF(J103>0,+$M$92-L103,0) -> 0 | L103: =+J103*$K$92/12*$K$91 -> 0 | M103: =IF(J103>1,J103-K103,0) -> 0
C104: TOTALE ANNO | D104: 2 | E104: =SUM(E100:E103) -> 0 | F104: =SUM(F100:F103) -> 0 | G104: =+G103 -> 0 | I104: TOTALE ANNO | J104: 2 | K104: =SUM(K100:K103) -> 0 | L104: =SUM(L100:L103) -> 0 | M104: =+M103 -> 0
C105: 9 | D105: =+G103 -> 0 | E105: =IF(D105>0,+$G$92-F105,0) -> 0 | F105: =+D105*$E$92/12*$E$91 -> 0 | G105: =IF(D105>1,D105-E105,0) -> 0 | I105: 9 | J105: =+M103 -> 0 | K105: =IF(J105>0,+$M$92-L105,0) -> 0 | L105: =+J105*$K$92/12*$K$91 -> 0 | M105: =IF(J105>1,J105-K105,0) -> 0
C106: 10 | D106: =+G105 -> 0 | E106: =IF(D106>0,+$G$92-F106,0) -> 0 | F106: =+D106*$E$92/12*$E$91 -> 0 | G106: =IF(D106>1,D106-E106,0) -> 0 | I106: 10 | J106: =+M105 -> 0 | K106: =IF(J106>0,+$M$92-L106,0) -> 0 | L106: =+J106*$K$92/12*$K$91 -> 0 | M106: =IF(J106>1,J106-K106,0) -> 0
C107: 11 | D107: =+G106 -> 0 | E107: =IF(D107>0,+$G$92-F107,0) -> 0 | F107: =+D107*$E$92/12*$E$91 -> 0 | G107: =IF(D107>1,D107-E107,0) -> 0 | I107: 11 | J107: =+M106 -> 0 | K107: =IF(J107>0,+$M$92-L107,0) -> 0 | L107: =+J107*$K$92/12*$K$91 -> 0 | M107: =IF(J107>1,J107-K107,0) -> 0
...
